deep_task_solver/__init__.py
deep_task_solver/client.py
deep_task_solver/exceptions.py
deep_task_solver-0.1.0.dist-info/licenses/LICENSE
deep_task_solver-0.1.0.dist-info/METADATA
deep_task_solver-0.1.0.dist-info/WHEEL
deep_task_solver-0.1.0.dist-info/top_level.txt
deep_task_solver-0.1.0.dist-info/RECORD
