Metadata-Version: 2.4
Name: deep-task-solver
Version: 0.1.0
Summary: Простая pip-библиотека для отправки задач в DeepSeek
Author-email: YOUR NAME <you@example.com>
License: MIT
Project-URL: Homepage, https://github.com/yourname/deep-task-solver
Requires-Python: >=3.8
License-File: LICENSE
Requires-Dist: requests>=2.31
Dynamic: license-file
